AdvanceCalculator/__init__.py
AdvanceCalculator/main.py
AdvanceCalculator/methods/__init__.py
AdvanceCalculator/methods/calculator.py
AdvanceCalculator/methods/calculus.py
AdvanceCalculator/methods/check_inputs.py
AdvanceCalculator/methods/plots.py
AdvanceCalculator/utility/__init__.py
AdvanceCalculator/utility/ui.py
AdvanceCalculatorProject-0.0.2.dist-info/METADATA
AdvanceCalculatorProject-0.0.2.dist-info/WHEEL
AdvanceCalculatorProject-0.0.2.dist-info/top_level.txt
AdvanceCalculatorProject-0.0.2.dist-info/RECORD
