Metadata-Version: 2.1
Name: AdvanceCalculatorProject
Version: 0.0.2
Summary: Simple advance calculator 
Author: Napain (Simon Torrealba)
Author-email: storrealba24@gmail.com
Keywords: python,calculus,ploting,solver,calculator
Requires-Dist: simpy
Requires-Dist: numpy
